Metadata-Version: 2.1
Name: etriai-whisper
Version: 20231117
Summary: Robust Speech Recognition via Large-Scale Weak Supervision
Home-page: https://github.com/openai/whisper
Author: Original: OpenAI, Revised: ETRI
License: MIT
Platform: UNKNOWN
Requires-Python: >=3.8
Provides-Extra: dev
